flapp/__init__.py
flapp/di.py
flapp/persistence/__init__.py
flapp/persistence/connection.py
flapp/persistence/dao.py
flapp/persistence/persistent_object.py
flapp/validation/__init__.py
flapp/validation/rules.py
flapp/validation/validator.py
flapp/web/__init__.py
flapp/web/auth.py
flapp/web/rest.py
flapp-0.0.1.dist-info/LICENSE
flapp-0.0.1.dist-info/METADATA
flapp-0.0.1.dist-info/WHEEL
flapp-0.0.1.dist-info/top_level.txt
flapp-0.0.1.dist-info/RECORD
