Metadata-Version: 2.1
Name: flapp
Version: 0.0.1
Summary: Flask application framework
Home-page: https://github.com/ignusin/flapp
Author: Iakov Gnusin
Author-email: y.gnusin@gmail.com
License: UNKNOWN
Platform: UNKNOWN
Classifier: Programming Language :: Python :: 3
Classifier: License :: OSI Approved :: MIT License
Classifier: Operating System :: OS Independent
